{"nick_no": "206746174", "code": "c3125", "nick_nm": "tonsh", "rank": "70"}
{"nick_no": "200996545", "code": "c3125", "nick_nm": "Zoenth", "rank": "70"}
{"nick_no": "137362013", "code": "c1062", "nick_nm": "\u53f2\u8a697\u306e\u672b\u65e5", "rank": "70"}
{"nick_no": "96733998", "code": "c1106", "nick_nm": "PengSky", "rank": "70"}
{"nick_no": "89214998", "code": "c2062", "nick_nm": "\u5c0f\u8c46\u6ca2\u3053\u306f\u306d", "rank": "70"}
{"nick_no": "77692858", "code": "c2062", "nick_nm": "seanoops", "rank": "70"}
{"nick_no": "77540440", "code": "c6062", "nick_nm": "\u7b49\u4ef7\u4ea4\u6362", "rank": "70"}
{"nick_no": "71212252", "code": "c5089", "nick_nm": "IOMEGAI", "rank": "70"}
{"nick_no": "64749738", "code": "c2037", "nick_nm": "wolf910", "rank": "70"}
{"nick_no": "61292097", "code": "c2023", "nick_nm": "\u5f20\u67cf\u829d", "rank": "70"}
{"nick_no": "61284190", "code": "c2089", "nick_nm": "Tzzzq", "rank": "70"}
{"nick_no": "61244626", "code": "c1151", "nick_nm": "Haku\u5973\u795e", "rank": "70"}
{"nick_no": "219381188", "code": "c6037", "nick_nm": "FerrumQ", "rank": "70"}
{"nick_no": "175764586", "code": "c1151", "nick_nm": "xKirax", "rank": "70"}
{"nick_no": "159161103", "code": "c5089", "nick_nm": "Akane\u9ed2\u5ddd", "rank": "70"}
{"nick_no": "158980767", "code": "c1132", "nick_nm": "leejaemyung", "rank": "70"}
{"nick_no": "155766830", "code": "c1123", "nick_nm": "DILU", "rank": "70"}
{"nick_no": "135514142", "code": "c2062", "nick_nm": "ThyOdyssey", "rank": "70"}
{"nick_no": "124477725", "code": "c2101", "nick_nm": "PortalKung", "rank": "70"}
{"nick_no": "120946886", "code": "c1066", "nick_nm": "\u651d\u9b42", "rank": "70"}
{"nick_no": "119474353", "code": "c1088", "nick_nm": "5\ub300\uae30", "rank": "70"}
{"nick_no": "108278375", "code": "c1081", "nick_nm": "WiseGuY\u667a", "rank": "70"}
{"nick_no": "107082874", "code": "c5082", "nick_nm": "Angbak", "rank": "70"}
{"nick_no": "94632732", "code": "c1083", "nick_nm": "kaif", "rank": "70"}
{"nick_no": "88691008", "code": "c4001", "nick_nm": "\u90a3\u4e2a\u8ab0", "rank": "70"}
{"nick_no": "77689700", "code": "c2087", "nick_nm": "Vesamau", "rank": "70"}
{"nick_no": "72065307", "code": "c6017", "nick_nm": "\u4e91\u4e0a\u6ce5\u91cc\u6d6a\u6f2b\u81ea\u7531", "rank": "70"}
{"nick_no": "68325226", "code": "m0045", "nick_nm": "\u6cf0\u5c3c\u6279\u91cc\u7684\u86c6", "rank": "70"}
{"nick_no": "66968421", "code": "c2050", "nick_nm": "\u9999\u83dc\u7092\u82e6\u74dc", "rank": "70"}
{"nick_no": "63441235", "code": "c2050", "nick_nm": "DukeSidew", "rank": "70"}
{"nick_no": "63436350", "code": "c2062", "nick_nm": "\u4f11\u6770\u514b\u66fc\u7684\u8001\u516c", "rank": "70"}
{"nick_no": "62028796", "code": "c1137", "nick_nm": "\u30fbVergil\u30fb", "rank": "70"}
{"nick_no": "60928854", "code": "c2009", "nick_nm": "\u547d\u8fd0\u77f3\u4e4b\u95e8\u7684\u6289\u62e9", "rank": "70"}
{"nick_no": "191627751", "code": "c3113", "nick_nm": "Sehprize", "rank": "70"}
{"nick_no": "163648368", "code": "c1151", "nick_nm": "\u65e0\u5984\u5c01\u6b32", "rank": "70"}
{"nick_no": "142473403", "code": "c2099", "nick_nm": "\u7ae0\u9b5a\u62c9\u573e\u6876", "rank": "70"}
{"nick_no": "105631633", "code": "c6011", "nick_nm": "\u6ce2\u6fe4\u6d36\u6e67\u7684\u5361\u7433", "rank": "70"}
{"nick_no": "103052675", "code": "c1151", "nick_nm": "\u5948\u514b\u745f\u65af\u5965\u7279\u6162", "rank": "70"}
{"nick_no": "84386876", "code": "c1151", "nick_nm": "\u671b\u6708\u7d05\u8449", "rank": "70"}
{"nick_no": "82282613", "code": "c1017", "nick_nm": "\u51c9\u98ce\u6709\u4fe1\u79cb\u6708\u65e0\u8fb9", "rank": "70"}
{"nick_no": "81744601", "code": "c5024", "nick_nm": "Berylpy\u901f", "rank": "70"}
{"nick_no": "81493272", "code": "c3134", "nick_nm": "\u4fee\u723e\u514b", "rank": "70"}
{"nick_no": "75427150", "code": "c2062", "nick_nm": "Icetaila", "rank": "70"}
{"nick_no": "75181003", "code": "c1050", "nick_nm": "\u590f\u8389\u6b27", "rank": "70"}
{"nick_no": "73917735", "code": "c2049", "nick_nm": "\u963f\u683c\u8389\u5a05\u65af", "rank": "70"}
{"nick_no": "73611475", "code": "c5050", "nick_nm": "\u30b7\u30c9\u30fb\u30ab\u30b2\u30ce\u30fc", "rank": "70"}
{"nick_no": "71031378", "code": "c2062", "nick_nm": "\u514b\u7df9\u5361\u5152\u8482", "rank": "70"}
{"nick_no": "63102749", "code": "c1151", "nick_nm": "\u72ec\u5b64\u4e5d\u5251", "rank": "70"}
{"nick_no": "61171745", "code": "c2070", "nick_nm": "Shiok\u708e", "rank": "70"}
{"nick_no": "213141988", "code": "c2073", "nick_nm": "\u9752\u79be\u79be\u79be\u79be", "rank": "70"}
{"nick_no": "199576587", "code": "c2062", "nick_nm": "juicykaraage", "rank": "70"}
{"nick_no": "171191031", "code": "c1018", "nick_nm": "otonokolover", "rank": "70"}
{"nick_no": "162380620", "code": "c1141", "nick_nm": "Farex\u011d", "rank": "70"}
{"nick_no": "137537222", "code": "c2009", "nick_nm": "Bobu", "rank": "70"}
{"nick_no": "126336601", "code": "c2046", "nick_nm": "\u5b89\u5357\u79c0\u79c0", "rank": "70"}
{"nick_no": "90145715", "code": "c2109", "nick_nm": "TimeDrain", "rank": "70"}
{"nick_no": "84060719", "code": "c1151", "nick_nm": "\u9752\u5c71\u4e09\u6c34\u58fd", "rank": "70"}
{"nick_no": "76852538", "code": "c2095", "nick_nm": "\u624e\u9a6c\u5c3e\u7684\u7537\u4eba", "rank": "70"}
{"nick_no": "74401923", "code": "c1117", "nick_nm": "\u6b65\u4f3a\u914c", "rank": "70"}
{"nick_no": "71453646", "code": "c2074", "nick_nm": "AtlasXVI", "rank": "70"}
{"nick_no": "69538409", "code": "c2062", "nick_nm": "\u6ce2\u591a\u91ce\u7d50\u8863\u30d5\u30a1\u30f3", "rank": "70"}
{"nick_no": "68484272", "code": "c6017", "nick_nm": "Aizu\u795e\u901f", "rank": "70"}
{"nick_no": "67874532", "code": "c6037", "nick_nm": "\u6700\u7231\u5927\u5c41\u5c41", "rank": "70"}
{"nick_no": "64046959", "code": "c1145", "nick_nm": "\u6c23\u6c96\u96f2\u6c34", "rank": "70"}
{"nick_no": "62284562", "code": "c6037", "nick_nm": "Shiro\u30c4", "rank": "70"}
{"nick_no": "60987275", "code": "c2062", "nick_nm": "\u5c11\u5973\u7684\u6551\u8d4e", "rank": "70"}
{"nick_no": "151159676", "code": "c2101", "nick_nm": "NoKanzaki", "rank": "70"}
{"nick_no": "149340714", "code": "c1150", "nick_nm": "o0FBI0o", "rank": "70"}
{"nick_no": "130599173", "code": "c1079", "nick_nm": "Brycester2", "rank": "70"}
{"nick_no": "124430812", "code": "c1072", "nick_nm": "\u5947\u9675\u5929", "rank": "70"}
{"nick_no": "98799274", "code": "c2047", "nick_nm": "epic7#cp2q0t", "rank": "70"}
{"nick_no": "77041625", "code": "c1151", "nick_nm": "\u70cf\u9f9c\u306e\u901f", "rank": "70"}
{"nick_no": "72471094", "code": "c1145", "nick_nm": "\u5361\u5361\u5c0f\u7f16", "rank": "70"}
{"nick_no": "71595412", "code": "m0073", "nick_nm": "\u4e0d\u9069\u7576\u7684\u66b1\u7a317", "rank": "70"}
{"nick_no": "63717415", "code": "c0002", "nick_nm": "\u503c\u5f97\u4fe1\u8cf4\u7684\u5925\u4f34", "rank": "70"}
{"nick_no": "61786046", "code": "c2111", "nick_nm": "\u53e0\u4e2a\u5343\u7eb8\u9e64", "rank": "70"}
{"nick_no": "262143099", "code": "c2070", "nick_nm": "DokiToki", "rank": "70"}
{"nick_no": "261081834", "code": "c6011", "nick_nm": "Eveer", "rank": "70"}
{"nick_no": "258969803", "code": "c6017", "nick_nm": "\u9189\u5624\u5c45\u58eb", "rank": "70"}
{"nick_no": "258432109", "code": "c1145", "nick_nm": "Brieg", "rank": "70"}
{"nick_no": "238172505", "code": "c1091", "nick_nm": "CurbEx", "rank": "70"}
{"nick_no": "202914427", "code": "c2037", "nick_nm": "\u661f\u91ce\u9732\u6bd4", "rank": "70"}
{"nick_no": "158641840", "code": "c6037", "nick_nm": "Azherothe", "rank": "70"}
{"nick_no": "157548288", "code": "c2101", "nick_nm": "MyLitlELoL7P", "rank": "70"}
{"nick_no": "156301705", "code": "c5149", "nick_nm": "\u5f02\u754c\u4fee\u9f99", "rank": "70"}
{"nick_no": "135325471", "code": "c4105", "nick_nm": "\u5f69\u7e6a\u5149\u74b0", "rank": "70"}
{"nick_no": "130276336", "code": "c1133", "nick_nm": "\u82cd\u4e4b\u4e16\u754c", "rank": "70"}
{"nick_no": "128389547", "code": "c2050", "nick_nm": "Shirori7", "rank": "70"}
{"nick_no": "106410070", "code": "c2101", "nick_nm": "\u8679\u590f\u5c0f\u5929\u4f7f", "rank": "70"}
{"nick_no": "81168756", "code": "c1112", "nick_nm": "\u4e00\u4e2a\u840c\u65b0", "rank": "70"}
{"nick_no": "79275103", "code": "c2101", "nick_nm": "\u5979\u9177\u7684\u50cf\u51b0", "rank": "70"}
{"nick_no": "76610022", "code": "c2042", "nick_nm": "\u4f5b\u7cfb\u914b\u957f", "rank": "70"}
{"nick_no": "76549053", "code": "c2023", "nick_nm": "\uc18d\ub3c4Hanbi", "rank": "70"}
{"nick_no": "75723938", "code": "c5089", "nick_nm": "\u524d\u5c18\u4e44\u5fc6\u68a6", "rank": "70"}
{"nick_no": "73301343", "code": "c2101", "nick_nm": "\u753b\u6708\u9501\u5929", "rank": "70"}
{"nick_no": "70982032", "code": "c2101", "nick_nm": "\u7dad\u5305\u5b50", "rank": "70"}
{"nick_no": "65799678", "code": "c3084", "nick_nm": "\u5927\u5922\u7121\u6daf", "rank": "70"}
{"nick_no": "61560263", "code": "c1106", "nick_nm": "ReikaMae", "rank": "70"}
{"nick_no": "60329760", "code": "c1131", "nick_nm": "3sixty", "rank": "70"}
{"nick_no": "213502060", "code": "c1141", "nick_nm": "\u5c3c\u6839", "rank": "70"}
{"nick_no": "166267585", "code": "c2111", "nick_nm": "rentann", "rank": "70"}
{"nick_no": "137145229", "code": "c2070", "nick_nm": "SparroW0312", "rank": "70"}
{"nick_no": "136752908", "code": "c1107", "nick_nm": "nut\u9f9f", "rank": "70"}
{"nick_no": "135577799", "code": "c2062", "nick_nm": "Misane", "rank": "70"}
{"nick_no": "121716107", "code": "c2009", "nick_nm": "\u674e\u8001\u516b", "rank": "70"}
{"nick_no": "106972453", "code": "c2101", "nick_nm": "DrakeHeart", "rank": "70"}
{"nick_no": "80143521", "code": "c1134", "nick_nm": "Mikey452", "rank": "70"}
{"nick_no": "78298984", "code": "c2047", "nick_nm": "\u4e00\u8272\u5f69\u7fbd", "rank": "70"}
{"nick_no": "76887620", "code": "c2101", "nick_nm": "\u8868\u91cc\u4e0d\u4e00\u6363\u86cb\u864eo", "rank": "70"}
{"nick_no": "73271429", "code": "c1151", "nick_nm": "ColbyAlphaAn", "rank": "70"}
{"nick_no": "71559401", "code": "c2074", "nick_nm": "Chakey", "rank": "70"}
{"nick_no": "68673050", "code": "c2082", "nick_nm": "\u6c34\u6298", "rank": "70"}
{"nick_no": "68337336", "code": "c1103", "nick_nm": "\u4e0d\u8981\u8fb9\u4e2d\u51fa\u8fb9\u62b1\u6b49", "rank": "70"}
{"nick_no": "64138331", "code": "c2101", "nick_nm": "\u7ea2\u8c46\u306b\u91cc\u7684\u7ea2\u8c46\u3060", "rank": "70"}
{"nick_no": "63748043", "code": "c2062", "nick_nm": "\u5922\u6708\u30ed\u30a2", "rank": "70"}
{"nick_no": "201334387", "code": "c2062", "nick_nm": "\u7a7a\u767d\u6c38\u4e0d\u8d25\u5317i", "rank": "70"}
{"nick_no": "137183805", "code": "c1028", "nick_nm": "Tengekyo", "rank": "70"}
{"nick_no": "136322528", "code": "c5089", "nick_nm": "Thi\u304f\u3093", "rank": "70"}
{"nick_no": "96756836", "code": "m0044", "nick_nm": "\u6211\u63a8\u7684\u8f68\u5b50", "rank": "70"}
{"nick_no": "92049651", "code": "c1137", "nick_nm": "\u9999\u83b1\u7092\u82e6\u74dc", "rank": "70"}
{"nick_no": "76989839", "code": "c1109", "nick_nm": "\ub791\ub514", "rank": "70"}
{"nick_no": "75622777", "code": "c1114", "nick_nm": "\u730e\u5947\u306e\u840c\u5927\u5927", "rank": "70"}
{"nick_no": "75400444", "code": "c2049", "nick_nm": "StarMaidLevi", "rank": "70"}
{"nick_no": "75253100", "code": "c1110", "nick_nm": "LiLXDeviL", "rank": "70"}
{"nick_no": "74266199", "code": "c1123", "nick_nm": "\u5b0c\u7228\u92e6\u9aa2", "rank": "70"}
{"nick_no": "71407989", "code": "c2099", "nick_nm": "\u91cc\u898b\u5149\u94bb", "rank": "70"}
{"nick_no": "69687421", "code": "c2071", "nick_nm": "Xman\u4e28\u5143\u9f99", "rank": "70"}
{"nick_no": "65504157", "code": "c5016", "nick_nm": "\u94f6\u8272\u306e\u8346\u68d8", "rank": "70"}
{"nick_no": "63262516", "code": "c2082", "nick_nm": "Syndia", "rank": "70"}
{"nick_no": "63033290", "code": "c1062", "nick_nm": "\u7121\u6575\u306e\u5b89\u6f54\u8389\u5361", "rank": "70"}
{"nick_no": "214346453", "code": "c4144", "nick_nm": "\u5e0c\u82b8", "rank": "70"}
{"nick_no": "203902306", "code": "c6037", "nick_nm": "epic7#bf5fii", "rank": "70"}
{"nick_no": "203576984", "code": "c2102", "nick_nm": "\u5c0f\u5c0f\u767d\u4e0e\u5c0f\u5c0f\u9ed1", "rank": "70"}
{"nick_no": "200099456", "code": "c2050", "nick_nm": "Hyouzan", "rank": "70"}
{"nick_no": "178457363", "code": "c1105", "nick_nm": "\u52a0\u85e4\u82f1\u7f8e\u91cc", "rank": "70"}
{"nick_no": "173308874", "code": "c1132", "nick_nm": "\u5c0f\u61d2\u72d7", "rank": "70"}
{"nick_no": "168639299", "code": "c4003", "nick_nm": "Marchen\u30e1", "rank": "70"}
{"nick_no": "163499397", "code": "c2099", "nick_nm": "\u597d\u591a\u4e1c\u897f", "rank": "70"}
{"nick_no": "144734168", "code": "c6037", "nick_nm": "xevenn", "rank": "70"}
{"nick_no": "108330667", "code": "c3074", "nick_nm": "TheMissing", "rank": "70"}
{"nick_no": "81723028", "code": "c2102", "nick_nm": "\u660e\u65e5\u3060", "rank": "70"}
{"nick_no": "75664976", "code": "c1118", "nick_nm": "\u8bb0\u5ddd", "rank": "70"}
{"nick_no": "75170142", "code": "c6062", "nick_nm": "\u82b1\u706bemo", "rank": "70"}
{"nick_no": "72117670", "code": "c2101", "nick_nm": "\u5c3c\u5c14\u673a\u68b0\u7eaa\u5143", "rank": "70"}
{"nick_no": "66339513", "code": "c2024", "nick_nm": "\u6740\u624b", "rank": "70"}
{"nick_no": "65034849", "code": "c2037", "nick_nm": "\u963f\u54e9\u54e9", "rank": "70"}
{"nick_no": "62886101", "code": "c2089", "nick_nm": "Tlover", "rank": "70"}
{"nick_no": "276328635", "code": "c2050", "nick_nm": "\u5e73\u5e38\u4e36\u5c0f\u602a\u517d", "rank": "70"}
{"nick_no": "164659099", "code": "c2103", "nick_nm": "XCWyyds", "rank": "70"}
{"nick_no": "128097806", "code": "c2071", "nick_nm": "\u4f55\u8655\u6625\u6c5f\u7121\u6708\u660e", "rank": "70"}
{"nick_no": "125866029", "code": "c1112", "nick_nm": "\u8b02\u8877", "rank": "70"}
{"nick_no": "125132608", "code": "c2102", "nick_nm": "l\u5468\u6811\u4ebal", "rank": "70"}
{"nick_no": "124682864", "code": "c2109", "nick_nm": "AigHtworthy", "rank": "70"}
{"nick_no": "124230279", "code": "c2071", "nick_nm": "\u591c\u96e8\u633d\u98ce", "rank": "70"}
{"nick_no": "122217206", "code": "c5089", "nick_nm": "tteokbi", "rank": "70"}
{"nick_no": "119651094", "code": "c5009", "nick_nm": "\u5e78\u904b\u5c0f\u6069", "rank": "70"}
{"nick_no": "94878087", "code": "c1151", "nick_nm": "\u795e\u80e4\u306e\u4e82\u821e", "rank": "70"}
{"nick_no": "88765301", "code": "c2074", "nick_nm": "Fenrear", "rank": "70"}
{"nick_no": "84555838", "code": "c2090", "nick_nm": "Syn\u00f8x", "rank": "70"}
{"nick_no": "75804897", "code": "c2101", "nick_nm": "\u4f0a\u529b\u9e92\u6bbf\u4e0b", "rank": "70"}
{"nick_no": "74488610", "code": "c6011", "nick_nm": "\u6000\u83cf\u65ad", "rank": "70"}
{"nick_no": "72759377", "code": "c2111", "nick_nm": "SayByeBaby", "rank": "70"}
{"nick_no": "72586669", "code": "c5089", "nick_nm": "\u6668\u66e6\u79cb\u666f", "rank": "70"}
{"nick_no": "70660081", "code": "c1128", "nick_nm": "\u559c\u4ed4", "rank": "70"}
{"nick_no": "70399156", "code": "c2062", "nick_nm": "TylerColbe", "rank": "70"}
{"nick_no": "69080327", "code": "c2074", "nick_nm": "BlairIngraAd", "rank": "70"}
{"nick_no": "69041691", "code": "c2062", "nick_nm": "\u8354\u679d\u4e00\u70b9", "rank": "70"}
{"nick_no": "65701448", "code": "c4144", "nick_nm": "\u7a7a\u767d\u767d\u767d", "rank": "70"}
{"nick_no": "61847523", "code": "c4144", "nick_nm": "\u5f13\u51a2\u4e94\u6708", "rank": "70"}
{"nick_no": "60318226", "code": "c2062", "nick_nm": "\u5e7b\u73a5\u6eaf\u6afb", "rank": "70"}
